<?xml version="1.0"?>
<liquidwar6>
  <float key="warp-x" value="0.1" />
  <float key="warp-y" value="0.1" />
  <float key="mode-sleep" value="0.0" />
  <float key="quit-sleep" value="0.01" />
  <int key="keysym1-up" value="273" /> <!-- SDLK_UP -->
  <int key="keysym2-up" value="263" /> <!-- SDLK_KP7 -->
  <int key="keysym3-up" value="264" /> <!-- SDLK_KP8 -->
  <int key="keysym4-up" value="265" /> <!-- SDLK_KP9 -->
  <int key="keysym1-down" value="274" /> <!-- SDLK_DOWN -->
  <int key="keysym2-down" value="257" /> <!-- SDLK_KP1 -->
  <int key="keysym3-down" value="258" /> <!-- SDLK_KP2 -->
  <int key="keysym4-down" value="259" /> <!-- SDLK_KP3 -->
  <int key="keysym1-left" value="276" /> <!-- SDLK_LEFT -->
  <int key="keysym2-left" value="257" /> <!-- SDLK_KP1 -->
  <int key="keysym3-left" value="260" /> <!-- SDLK_KP4 -->
  <int key="keysym4-left" value="263" /> <!-- SDLK_KP7 -->
  <int key="keysym1-right" value="275" /> <!-- SDLK_RIGHT -->
  <int key="keysym2-right" value="259" /> <!-- SDLK_KP3 -->
  <int key="keysym3-right" value="262" /> <!-- SDLK_KP6 -->
  <int key="keysym4-right" value="265" /> <!-- SDLK_KP9 -->
  <int key="keysym1-enter" value="13" /> <!-- SDLK_RETURN -->
  <int key="keysym2-enter" value="271" /> <!-- SDLK_KP_ENTER -->
  <int key="keysym1-esc" value="27" /> <!-- SDLK_ESCAPE -->
  <int key="keysym2-esc" value="256" /> <!-- SDLK_KP0 -->
  <int key="keysym1-ctrl" value="305" /> <!-- SDLK_RCTRL -->
  <int key="keysym2-ctrl" value="306" /> <!-- SDLK_LCTRL -->
  <int key="keysym1-alt" value="307" /> <!-- SDLK_RALT -->
  <int key="keysym2-alt" value="308" /> <!-- SDLK_LALT -->
  <int key="keysym1-pgup" value="280" /> <!-- SDLK_PAGEUP -->
  <int key="keysym2-pgup" value="269" /> <!-- SDLK_KP_MINUS -->
  <int key="keysym1-pgdown" value="281" /> <!-- SDLK_PAGEDOWN -->
  <int key="keysym2-pgdown" value="270" /> <!-- SDLK_KP_PLUS -->
  <int key="keysym-quit" value="291" /> <!-- SDLK_F10 -->
  <int key="joystick-limit" value="16384" />
  <int key="joystick1-index" value="0" />
  <int key="joystick1-button-a-index" value="0" />
  <int key="joystick1-button-b-index" value="1" />
  <int key="joystick1-button-c-index" value="2" />
  <int key="joystick1-button-d-index" value="3" />
  <int key="joystick1-button-e-index" value="4" />
  <int key="joystick1-button-f-index" value="5" />
  <int key="joystick2-index" value="1" />
  <int key="joystick2-button-a-index" value="0" />
  <int key="joystick2-button-b-index" value="1" />
  <int key="joystick2-button-c-index" value="2" />
  <int key="joystick2-button-d-index" value="3" />
  <int key="joystick2-button-e-index" value="4" />
  <int key="joystick2-button-f-index" value="5" />
  <bool key="joystick-all-buttons" value="true" />
</liquidwar6>
